neutralityFR
