Metadata-Version: 1.0
Name: django-neutralityFR
Version: 0.1.2
Summary: Middleware Django anti-netneutrality to give an example to some people.
Home-page: https://github.com/cyberj/django-neutralityFR
Author: Johan Charpentier
Author-email: cyberj@arcagenis.org
License: MIT
Platform: UNKNOWN
Classifier: Programming Language :: Python
Classifier: Framework :: Django
Classifier: License :: OSI Approved :: MIT License
